MANIFEST.in
README.txt
setup.py
dist/plonetheme.ewb_case-0.1.1/README.txt
dist/plonetheme.ewb_case-0.1.1/setup.py
dist/plonetheme.ewb_case-0.1.1/docs/HISTORY.txt
dist/plonetheme.ewb_case-0.1.1/docs/INSTALL.txt
dist/plonetheme.ewb_case-0.1.1/plonetheme/__init__.py
dist/plonetheme.ewb_case-0.1.1/plonetheme.ewb_case.egg-info/SOURCES.txt
dist/plonetheme.ewb_case-0.1.1/plonetheme.ewb_case.egg-info/dependency_links.txt
dist/plonetheme.ewb_case-0.1.1/plonetheme.ewb_case.egg-info/entry_points.txt
dist/plonetheme.ewb_case-0.1.1/plonetheme.ewb_case.egg-info/namespace_packages.txt
dist/plonetheme.ewb_case-0.1.1/plonetheme.ewb_case.egg-info/requires.txt
dist/plonetheme.ewb_case-0.1.1/plonetheme.ewb_case.egg-info/top_level.txt
dist/plonetheme.ewb_case-0.1.1/plonetheme/ewb_case/README.txt
dist/plonetheme.ewb_case-0.1.1/plonetheme/ewb_case/__init__.py
dist/plonetheme.ewb_case-0.1.1/plonetheme/ewb_case/configure.zcml
dist/plonetheme.ewb_case-0.1.1/plonetheme/ewb_case/interfaces.py
dist/plonetheme.ewb_case-0.1.1/plonetheme/ewb_case/profiles.zcml
dist/plonetheme.ewb_case-0.1.1/plonetheme/ewb_case/skins.zcml
dist/plonetheme.ewb_case-0.1.1/plonetheme/ewb_case/util.py
dist/plonetheme.ewb_case-0.1.1/plonetheme/ewb_case/version.txt
dist/plonetheme.ewb_case-0.1.1/plonetheme/ewb_case/browser/__init__.py
dist/plonetheme.ewb_case-0.1.1/plonetheme/ewb_case/browser/configure.zcml
dist/plonetheme.ewb_case-0.1.1/plonetheme/ewb_case/browser/controlpanel.py
dist/plonetheme.ewb_case-0.1.1/plonetheme/ewb_case/browser/ewb_caseview.py
dist/plonetheme.ewb_case-0.1.1/plonetheme/ewb_case/browser/interfaces.py
dist/plonetheme.ewb_case-0.1.1/plonetheme/ewb_case/browser/navigation.py
dist/plonetheme.ewb_case-0.1.1/plonetheme/ewb_case/browser/viewlets.py
dist/plonetheme.ewb_case-0.1.1/plonetheme/ewb_case/browser/templates/footer.pt
dist/plonetheme.ewb_case-0.1.1/plonetheme/ewb_case/browser/templates/header_tabs.pt
dist/plonetheme.ewb_case-0.1.1/plonetheme/ewb_case/browser/templates/labeled_sections.pt
dist/plonetheme.ewb_case-0.1.1/plonetheme/ewb_case/browser/templates/logo.pt
dist/plonetheme.ewb_case-0.1.1/plonetheme/ewb_case/browser/templates/path_bar.pt
dist/plonetheme.ewb_case-0.1.1/plonetheme/ewb_case/browser/templates/personal_bar.pt
dist/plonetheme.ewb_case-0.1.1/plonetheme/ewb_case/browser/templates/searchbox.pt
dist/plonetheme.ewb_case-0.1.1/plonetheme/ewb_case/browser/templates/sections.pt
plonetheme.ewb_case.egg-info/PKG-INFO
plonetheme.ewb_case.egg-info/SOURCES.txt
plonetheme.ewb_case.egg-info/dependency_links.txt
plonetheme.ewb_case.egg-info/entry_points.txt
plonetheme.ewb_case.egg-info/namespace_packages.txt
plonetheme.ewb_case.egg-info/not-zip-safe
plonetheme.ewb_case.egg-info/requires.txt
plonetheme.ewb_case.egg-info/top_level.txt
