Metadata-Version: 1.0
Name: plonetheme.ewb_case
Version: 0.1.2
Summary: A Plone 4 theme for EWB Case
Home-page: https://github.com/mattbierner/plonetheme.ewb_case
Author: Matt Bierner
Author-email: mattbierner@gmail.com
License: Creative Commons Attribution 3.0 Unported
Platform: UNKNOWN
Classifier: Framework :: Plone
Classifier: Programming Language :: Python
Classifier: Development Status :: 4 - Beta
